{
    "column_width": {
        "0": 100, 
        "1": 50, 
        "3": 50, 
        "4": 50, 
        "5": 90, 
        "6": 100, 
        "7": 96, 
        "8": 131, 
        "9": 50, 
        "10": 50, 
        "11": 50
    }, 
    "table_data": {
        "column_desc": {}, 
        "data": [
            [
                "index", 
                "index_real", 
                "id", 
                "class", 
                "pop", 
                "name", 
                "name_img_1", 
                "name_img_2", 
                "avatar", 
                "1", 
                "2", 
                "3", 
                "4"
            ], 
            [
                "int", 
                "int", 
                "string", 
                "int", 
                "float", 
                "string", 
                "int", 
                "int", 
                "int", 
                "int", 
                "int", 
                "int", 
                "int"
            ], 
            [
                "1", 
                "1", 
                "134244052", 
                "3", 
                "3", 
                "NguyenYanra", 
                "", 
                "134232823", 
                "134266201", 
                "1", 
                "1", 
                "1", 
                "1"
            ], 
            [
                "2", 
                "2", 
                "134252718", 
                "3", 
                "3", 
                "ZhangMengbai", 
                "", 
                "134241727", 
                "134276810", 
                "1", 
                "1", 
                "1", 
                "1"
            ], 
            [
                "3", 
                "3", 
                "134258859", 
                "3", 
                "3", 
                "Mastersword", 
                "", 
                "134261425", 
                "134278924", 
                "1", 
                "1", 
                "1", 
                "1"
            ], 
            [
                "4", 
                "4", 
                "134277830", 
                "3", 
                "3", 
                "YinSusu", 
                "", 
                "134223202", 
                "134265067", 
                "1", 
                "1", 
                "1", 
                "1"
            ], 
            [
                "5", 
                "5", 
                "134227024", 
                "3", 
                "3", 
                "Shira", 
                "", 
                "134252212", 
                "134225143", 
                "1", 
                "1", 
                "1", 
                "1"
            ], 
            [
                "6", 
                "6", 
                "134246222", 
                "3", 
                "3", 
                "Ragingfire", 
                "", 
                "134238900", 
                "134232634", 
                "1", 
                "1", 
                "1", 
                "1"
            ], 
            [
                "7", 
                "7", 
                "134250192", 
                "3", 
                "3", 
                "Well-informedear", 
                "", 
                "134237926", 
                "134270694", 
                "1", 
                "1", 
                "1", 
                "1"
            ], 
            [
                "8", 
                "8", 
                "134268762", 
                "3", 
                "3", 
                "clairvoyant", 
                "", 
                "134225718", 
                "134245112", 
                "1", 
                "1", 
                "1", 
                "1"
            ], 
            [
                "9", 
                "9", 
                "134240543", 
                "3", 
                "3", 
                "SunWukong", 
                "", 
                "134224951", 
                "134263643", 
                "1", 
                "1", 
                "1", 
                "1"
            ], 
            [
                null, 
                null, 
                null, 
                null, 
                null, 
                "", 
                null, 
                null, 
                null, 
                null, 
                null, 
                null, 
                null
            ], 
            [
                "10", 
                "10", 
                "134238493", 
                "3", 
                "3", 
                "Thebeginningofheaven", 
                "", 
                "134243276", 
                "134240111", 
                "1", 
                "1", 
                "1", 
                "1"
            ], 
            [
                null, 
                null, 
                null, 
                null, 
                null, 
                "", 
                null, 
                null, 
                null, 
                null, 
                null, 
                null, 
                null
            ], 
            [
                null, 
                null, 
                null, 
                null, 
                null, 
                "", 
                null, 
                null, 
                null, 
                null, 
                null, 
                null, 
                null
            ], 
            [
                null, 
                null, 
                null, 
                null, 
                null, 
                "", 
                null, 
                null, 
                null, 
                null, 
                null, 
                null, 
                null
            ], 
            [
                null, 
                null, 
                null, 
                null, 
                null, 
                "", 
                null, 
                null, 
                null, 
                null, 
                null, 
                null, 
                null
            ], 
            [
                null, 
                null, 
                null, 
                null, 
                null, 
                "", 
                null, 
                null, 
                null, 
                null, 
                null, 
                null, 
                null
            ], 
            [
                null, 
                null, 
                null, 
                null, 
                null, 
                "", 
                null, 
                null, 
                null, 
                null, 
                null, 
                null, 
                null
            ], 
            [
                null, 
                null, 
                null, 
                null, 
                null, 
                "", 
                null, 
                null, 
                null, 
                null, 
                null, 
                null, 
                null
            ], 
            [
                "11", 
                "11", 
                "134223134", 
                "3", 
                "3", 
                "Afaintshadowfellintheair.", 
                null, 
                "134248742", 
                "134257438", 
                "1", 
                "1", 
                "1", 
                "1"
            ]
        ], 
        "key": [
            0
        ]
    }, 
    "table_type": 0, 
    "tid": 15
}