{
    "action": [
        {
            "action_type": "PRINT_MESSAGE_ACTION_TO_DIALOG", 
            "args_list": [
                {
                    "arg_type": 100175, 
                    "args_list": [
                        3
                    ], 
                    "sub_type": 1
                }, 
                {
                    "arg_type": 100003, 
                    "args_list": [
                        {
                            "arg_type": 100003, 
                            "args_list": [
                                "游戏模式："
                            ], 
                            "sub_type": 1
                        }, 
                        {
                            "arg_type": 100003, 
                            "args_list": [
                                {
                                    "arg_type": 100002, 
                                    "args_list": [
                                        [
                                            "INTEGER", 
                                            "游戏模式"
                                        ]
                                    ], 
                                    "sub_type": 6
                                }
                            ], 
                            "sub_type": "ANY_VAR_TO_STR"
                        }
                    ], 
                    "op_arg": [
                        null, 
                        null, 
                        null, 
                        null, 
                        null, 
                        null, 
                        null, 
                        null
                    ], 
                    "op_arg_enable": [
                        false, 
                        false, 
                        false, 
                        false, 
                        false, 
                        false, 
                        false, 
                        false
                    ], 
                    "sub_type": "STR_JOIN"
                }
            ], 
            "bp": false, 
            "element_id": 246903190840258, 
            "enable": true
        }, 
        {
            "action_type": "PRINT_MESSAGE_ACTION_TO_DIALOG", 
            "args_list": [
                {
                    "arg_type": 100175, 
                    "args_list": [
                        3
                    ], 
                    "sub_type": 1
                }, 
                {
                    "arg_type": 100003, 
                    "args_list": [
                        {
                            "arg_type": 100003, 
                            "args_list": [
                                "游戏子模式："
                            ], 
                            "sub_type": 1
                        }, 
                        {
                            "arg_type": 100003, 
                            "args_list": [
                                {
                                    "arg_type": 100002, 
                                    "args_list": [
                                        [
                                            "INTEGER", 
                                            "游戏子模式"
                                        ]
                                    ], 
                                    "sub_type": 6
                                }
                            ], 
                            "sub_type": "ANY_VAR_TO_STR"
                        }
                    ], 
                    "op_arg": [
                        null, 
                        null, 
                        null, 
                        null, 
                        null, 
                        null, 
                        null, 
                        null
                    ], 
                    "op_arg_enable": [
                        false, 
                        false, 
                        false, 
                        false, 
                        false, 
                        false, 
                        false, 
                        false
                    ], 
                    "sub_type": "STR_JOIN"
                }
            ], 
            "bp": false, 
            "element_id": 246903190840261, 
            "enable": true
        }, 
        {
            "action_type": "PRINT_MESSAGE_ACTION_TO_DIALOG", 
            "args_list": [
                {
                    "arg_type": 100175, 
                    "args_list": [
                        3
                    ], 
                    "sub_type": 1
                }, 
                {
                    "arg_type": 100003, 
                    "args_list": [
                        {
                            "arg_type": 100003, 
                            "args_list": [
                                "所选英雄"
                            ], 
                            "sub_type": 1
                        }, 
                        {
                            "arg_type": 100003, 
                            "args_list": [
                                {
                                    "arg_type": 100002, 
                                    "args_list": [
                                        [
                                            "INTEGER", 
                                            "选择督军索引"
                                        ], 
                                        {
                                            "arg_type": 100002, 
                                            "args_list": [
                                                1
                                            ], 
                                            "sub_type": 1
                                        }
                                    ], 
                                    "sub_type": 6
                                }
                            ], 
                            "sub_type": "ANY_VAR_TO_STR"
                        }
                    ], 
                    "op_arg": [
                        null, 
                        null, 
                        null, 
                        null, 
                        null, 
                        null, 
                        null, 
                        null
                    ], 
                    "op_arg_enable": [
                        false, 
                        false, 
                        false, 
                        false, 
                        false, 
                        false, 
                        false, 
                        false
                    ], 
                    "sub_type": "STR_JOIN"
                }
            ], 
            "bp": false, 
            "element_id": 246903190840274, 
            "enable": true
        }, 
        {
            "action_type": "PAUSE_TIMER", 
            "args_list": [
                {
                    "arg_type": 100181, 
                    "args_list": [
                        [
                            "NEW_TIMER", 
                            "强制开始计时器"
                        ]
                    ], 
                    "sub_type": "VARIABLE"
                }
            ], 
            "bp": false, 
            "element_id": 246903190840277, 
            "enable": true
        }, 
        {
            "action_type": "RUN_ONCE_TIMER_NO_SAVE", 
            "args_list": [
                {
                    "arg_type": 100000, 
                    "args_list": [
                        3.0
                    ], 
                    "sub_type": 1
                }, 
                {
                    "arg_type": 100022, 
                    "args_list": [
                        {
                            "action_type": "FOR_INT_DO_ACTION", 
                            "args_list": [
                                {
                                    "arg_type": 100002, 
                                    "args_list": [
                                        {
                                            "__tuple__": true, 
                                            "items": [
                                                "INTEGER", 
                                                "索引", 
                                                "local"
                                            ]
                                        }
                                    ], 
                                    "sub_type": 6
                                }, 
                                {
                                    "arg_type": 100002, 
                                    "args_list": [
                                        1
                                    ], 
                                    "sub_type": 1
                                }, 
                                {
                                    "arg_type": 100002, 
                                    "args_list": [
                                        {
                                            "__tuple__": true, 
                                            "items": [
                                                "INTEGER", 
                                                "玩家数量"
                                            ]
                                        }
                                    ], 
                                    "sub_type": 6
                                }, 
                                {
                                    "arg_type": 100022, 
                                    "args_list": [
                                        {
                                            "action_type": "SEND_CUSTOM_EVENT", 
                                            "args_list": [
                                                {
                                                    "arg_type": 100238, 
                                                    "args_list": [
                                                        2065862999
                                                    ], 
                                                    "sub_type": 1
                                                }, 
                                                {
                                                    "arg_type": 100002, 
                                                    "args_list": [
                                                        {
                                                            "__tuple__": true, 
                                                            "items": [
                                                                "INTEGER", 
                                                                "索引", 
                                                                "local"
                                                            ]
                                                        }
                                                    ], 
                                                    "sub_type": 6
                                                }, 
                                                {
                                                    "arg_type": 100002, 
                                                    "args_list": [
                                                        3
                                                    ], 
                                                    "sub_type": 1
                                                }
                                            ], 
                                            "bp": false, 
                                            "element_id": 246903190000003, 
                                            "enable": true
                                        }
                                    ], 
                                    "sub_type": 1
                                }
                            ], 
                            "bp": false, 
                            "element_id": 246903190000004, 
                            "enable": true
                        }, 
                        [
                            1467840255, 
                            "参数 = 加载时间", 
                            1322119570, 
                            "action_type"
                        ], 
                        {
                            "action_type": "SEND_CUSTOM_EVENT", 
                            "args_list": [
                                {
                                    "arg_type": 100238, 
                                    "args_list": [
                                        1176440746
                                    ], 
                                    "sub_type": 1
                                }, 
                                {
                                    "arg_type": 100000, 
                                    "args_list": [
                                        3.0
                                    ], 
                                    "sub_type": 1
                                }
                            ], 
                            "bp": false, 
                            "element_id": 246903190000005, 
                            "enable": true
                        }
                    ], 
                    "sub_type": 1
                }
            ], 
            "bp": false, 
            "element_id": 246903190000006, 
            "enable": true, 
            "local_var": {
                "__tuple__": true, 
                "items": [
                    {}, 
                    {}
                ]
            }
        }
    ], 
    "call_enabled": true, 
    "condition": [
        {
            "args_list": [
                {
                    "arg_type": 100025, 
                    "args_list": [], 
                    "sub_type": "TRIGGER_PLAYER"
                }, 
                {
                    "arg_type": 100035, 
                    "args_list": [
                        "=="
                    ], 
                    "sub_type": 1
                }, 
                {
                    "arg_type": 100025, 
                    "args_list": [
                        1
                    ], 
                    "sub_type": 1
                }
            ], 
            "condition_type": "PLAYER_COMPARE", 
            "element_id": 246903190000002, 
            "enable": true
        }
    ], 
    "enabled": false, 
    "event": [
        {
            "args_list": [
                {
                    "arg_type": 100067, 
                    "args_list": [
                        "开始游戏按钮_0"
                    ], 
                    "sub_type": 1
                }
            ], 
            "element_id": 246903190000001, 
            "enable": true, 
            "event_type": "TRIGGER_COMPONENT_EVENT"
        }
    ], 
    "group_id": "iMhDQOeAEe6k48AlpZA-ST", 
    "p_trigger_id": null, 
    "trigger_id": 1322119570, 
    "trigger_name": "开始游戏房主", 
    "valid": true, 
    "var_data": [
        {
            "BOOLEAN": {}, 
            "INTEGER": {
                "索引": 0
            }
        }, 
        {
            "索引": 0
        }, 
        [
            "索引"
        ]
    ]
}